_pytask/__init__.py
_pytask/_hashlib.py
_pytask/_inspect.py
_pytask/_version.py
_pytask/build.py
_pytask/cache.py
_pytask/capture.py
_pytask/capture_utils.py
_pytask/clean.py
_pytask/cli.py
_pytask/click.py
_pytask/coiled_utils.py
_pytask/collect.py
_pytask/collect_command.py
_pytask/collect_utils.py
_pytask/compat.py
_pytask/config.py
_pytask/config_utils.py
_pytask/console.py
_pytask/dag.py
_pytask/dag_command.py
_pytask/dag_utils.py
_pytask/data_catalog.py
_pytask/data_catalog_utils.py
_pytask/database.py
_pytask/database_utils.py
_pytask/debugging.py
_pytask/exceptions.py
_pytask/execute.py
_pytask/explain.py
_pytask/git.py
_pytask/hookspecs.py
_pytask/live.py
_pytask/logging.py
_pytask/logging_utils.py
_pytask/mark_utils.py
_pytask/models.py
_pytask/node_protocols.py
_pytask/nodes.py
_pytask/outcomes.py
_pytask/parameters.py
_pytask/path.py
_pytask/persist.py
_pytask/pluginmanager.py
_pytask/profile.py
_pytask/provisional.py
_pytask/provisional_utils.py
_pytask/py.typed
_pytask/reports.py
_pytask/session.py
_pytask/shared.py
_pytask/skipping.py
_pytask/task.py
_pytask/task_utils.py
_pytask/traceback.py
_pytask/tree_util.py
_pytask/typing.py
_pytask/warnings.py
_pytask/warnings_utils.py
_pytask/mark/__init__.py
_pytask/mark/expression.py
_pytask/mark/structures.py
pytask/__init__.py
pytask/__main__.py
pytask/path.py
pytask/py.typed
pytask/tree_util.py
pytask-0.5.8.dist-info/METADATA
pytask-0.5.8.dist-info/WHEEL
pytask-0.5.8.dist-info/entry_points.txt
pytask-0.5.8.dist-info/licenses/LICENSE
pytask-0.5.8.dist-info/RECORD
