Metadata-Version: 2.4
Name: pytask
Version: 0.5.8
Summary: pytask is a workflow management system that facilitates reproducible data analyses.
Project-URL: Changelog, https://pytask-dev.readthedocs.io/en/stable/changes.html
Project-URL: Documentation, https://pytask-dev.readthedocs.io/en/stable
Project-URL: Github, https://github.com/pytask-dev/pytask
Project-URL: Homepage, https://pytask-dev.readthedocs.io/en/stable
Project-URL: Tracker, https://github.com/pytask-dev/pytask/issues
Author-email: Tobias Raabe <raabe@posteo.de>
License: MIT
License-File: LICENSE
Classifier: Development Status :: 4 - Beta
Classifier: Environment :: Console
Classifier: Intended Audience :: Science/Research
Classifier: License :: OSI Approved :: MIT License
Classifier: Operating System :: MacOS :: MacOS X
Classifier: Operating System :: Microsoft :: Windows
Classifier: Operating System :: POSIX
Classifier: Programming Language :: Python :: 3 :: Only
Classifier: Programming Language :: Python :: 3.10
Classifier: Programming Language :: Python :: 3.11
Classifier: Programming Language :: Python :: 3.12
Classifier: Programming Language :: Python :: 3.13
Classifier: Programming Language :: Python :: 3.14
Classifier: Topic :: Scientific/Engineering
Classifier: Topic :: Software Development :: Build Tools
Requires-Python: >=3.10
Requires-Dist: attrs>=21.3.0
Requires-Dist: click!=8.2.0,>=8.1.8
Requires-Dist: click-default-group>=1.2.4
Requires-Dist: networkx>=2.4.0
Requires-Dist: optree>=0.9.0
Requires-Dist: packaging>=23.0.0
Requires-Dist: pluggy>=1.3.0
Requires-Dist: rich>=13.8.0
Requires-Dist: sqlalchemy>=2.0.31
Requires-Dist: tomli>=1; python_version < '3.11'
Requires-Dist: typing-extensions>=4.8.0; python_version < '3.11'
Requires-Dist: universal-pathlib>=0.2.2
